{
	"1848_revolution_memorial_day": "Hari Peringatan Revolusi 1848",
	"1956_revolution_memorial_day": "Hari Peringatan Revolusi 1956",
	"2_january": "2 Januari",
	"adelaide_cup_day": "Hari Piala Adelaide",
	"africa_day": "Hari Afrika",
	"africa_day_heroes_day": "Hari Afrika/Hari Pahlawan",
	"agrarian_reform_day": "Hari Reformasi Agraria",
	"air_force_day": "Hari Angkatan Udara",
	"all_saints_day": "Hari Raya Semua Orang Kudus",
	"all_saints_day_eve": "Malam Hari Raya Semua Orang Kudus",
	"all_souls_day": "Hari Arwah",
	"amazigh_new_year": "Tahun Baru Amazigh",
	"america_s_day": "Hari Amerika",
	"ancestry_day": "Hari Leluhur",
	"andean_new_year": "Tahun Baru Andes",
	"annexation_of_the_party_of_nicoya_to_costa_rica": "Aneksasi Wilayah Nicoya ke Kosta Rika",
	"anniversary_of_the_arengo": "Peringatan Hari Jadi Arengo",
	"anniversary_of_the_battle_of_carabobo": "Peringatan Pertempuran Carabobo",
	"anniversary_of_the_passing_of_general_mart\u00edn_miguel_de_g\u00fcemes": "Peringatan Wafatnya Jenderal Mart\u00edn Miguel de G\u00fcemes",
	"annunciation": "Isyarat",
	"anti_fascist_struggle_day": "Hari Perjuangan AntiFasis",
	"anzac_day": "Hari Anzac",
	"april_fools_day": "Hari April Mop",
	"armed_forces_day": "Hari Angkatan Bersenjata",
	"armenian_genocide_remembrance_day": "Hari Peringatan Genosida Armenia",
	"armistice_day": "Hari Gencatan Senjata",
	"army_abolition_day": "Hari Penghapusan Angkatan Darat",
	"army_day": "Hari Angkatan Darat",
	"arrival_day": "Hari Kedatangan",
	"ascension_day": "Hari Kenaikan",
	"ash_wednesday": "Rabu Abu",
	"ashura": "Asyura",
	"assumption": "Anggapan",
	"assumption_day": "Hari Kenaikan",
	"assumption_of_mary": "Kenaikan Maria",
	"assumption_of_the_virgin_mary": "Kenaikan Perawan Maria",
	"atat\u00fcrk_commemoration_youth_day": "Peringatan Atat\u00fcrk &amp; Hari Pemuda",
	"auckland_anniversary_day": "Hari Peringatan Auckland",
	"august_festivals": "Festival Bulan Agustus",
	"august_holiday": "Liburan Agustus",
	"australia_day": "Hari Australia",
	"autumnal_equinox_day": "Hari Ekuinoks Musim Gugur",
	"azores_day": "Hari Azores",
	"bank_closing_day": "Hari penutupan bank",
	"bastille_day": "Hari Bastille",
	"battle_of_angamos": "Pertempuran Angamos",
	"battle_of_arica": "Pertempuran Arica",
	"battle_of_boyac\u00e1": "Pertempuran Boyac\u00e1",
	"battle_of_las_piedras": "Pertempuran Las Piedras",
	"battle_of_san_jacinto": "Pertempuran San Jacinto",
	"battle_of_the_boyne": "Pertempuran Boyne",
	"battle_of_verti\u00e8res_day": "Pertempuran Verti\u00e8res Hari",
	"beginning_of_the_independence_movement": "Awal Gerakan Kemerdekaan",
	"belgian_national_day": "Hari Nasional Belgia",
	"benito_ju\u00e1rez_s_birthday": "Ulang tahun Benito Ju\u00e1rez",
	"birth_of_the_blessed_virgin_mary": "Kelahiran Bunda Maria yang Terberkati",
	"birthday_of_don_luis_mu\u00f1oz_rivera": "Ulang Tahun Don Luis Mu\u00f1oz Rivera",
	"birthday_of_dr_jos\u00e9_celso_barbosa": "Ulang tahun Dr. Jos\u00e9 Celso Barbosa",
	"birthday_of_eugenio_mar\u00eda_de_hostos": "Ulang tahun Eugenio Mar\u00eda de Hostos",
	"birthday_of_jos\u00e9_de_diego": "Ulang Tahun Jos\u00e9 de Diego",
	"birthday_of_jos\u00e9_gervasio_artigas_and_never_again_day": "Hari Ulang Tahun Jos\u00e9 Gervasio Artigas dan Hari Tak Akan Terulang Lagi",
	"birthday_of_luis_mu\u00f1oz_mar\u00edn": "Ulang tahun Luis Mu\u00f1oz Mar\u00edn",
	"black_awareness_day": "Hari Kesadaran Kulit Hitam",
	"bonifacio_day": "Hari Bonifacio",
	"boqueron_battle_victory_day": "Hari Kemenangan Pertempuran Boqueron",
	"botswana_day_holiday": "Hari libur Botswana",
	"boxing_day": "Hari Boxing Day",
	"british_columbia_day": "Hari British Columbia",
	"buddha_s_birthday": "Hari Ulang Tahun Buddha",
	"b\u0103l\u0163i_day": "Hari B\u0103l\u0163i",
	"canada_day": "Hari Kanada",
	"canberra_day": "Hari Canberra",
	"candlemas": "Candlemas",
	"canterbury_anniversary_day": "Hari Peringatan Canterbury",
	"canterbury_south_anniversary_day": "Hari Peringatan Canterbury (Selatan)",
	"capital_city_day": "Hari Ibu Kota",
	"capital_s_day": "Hari Ibu Kota",
	"caracas_city_foundation_day": "Hari Pendirian Kota Caracas",
	"caricom_day": "Hari Caricom",
	"carnival": "Karnaval",
	"cassinga_day": "Hari Cassinga",
	"castile_and_le\u00f3n_day": "Castile dan Le\u00f3n Day",
	"catholicchristmas_day": "Hari Natal Katolik",
	"chaco_armistice": "Gencatan Senjata Chaco",
	"chatham_islands_anniversary_day": "Hari Peringatan Kepulauan Chatham",
	"children_s_day": "Hari Anak",
	"chinese_arrival_day": "Hari Kedatangan Warga Negara Tionghoa",
	"chinese_new_year": "Tahun Baru Imlek",
	"chinese_new_year_spring_festival_": "Tahun Baru Imlek (Festival Musim Semi)",
	"ching_ming_festival": "Festival Qing Ming",
	"christmas": "Natal",
	"christmas_day": "hari natal",
	"christmas_day_orthodox_": "Hari Natal (Ortodoks)",
	"christmas_day_roman_catholic_": "Hari Natal (Katolik Roma)",
	"christmas_eve": "malam Natal",
	"christmas_eve_orthodox_": "Malam Natal (Ortodoks)",
	"christmas_eve_roman_catholic_": "Malam Natal (Katolik Roma)",
	"chung_yeung_festival": "Festival Chung Yeung",
	"chuseok": "Chuseok",
	"civic_holiday": "Hari Libur Sipil",
	"clean_monday": "Senin Bersih-bersih",
	"colon_day": "Hari Usus Besar",
	"columbus_day": "Hari Columbus",
	"coming_of_age_day": "Hari Kedewasaan",
	"commemoration_day": "Hari Peringatan",
	"commemoration_of_all_those_who_died_at_war": "Peringatan bagi semua orang yang gugur dalam perang.",
	"commemoration_of_the_assault_of_the_moncada_garrison": "Peringatan Penyerangan Garnisun Moncada",
	"commerce_day": "Hari Perdagangan",
	"commonwealth_day": "Hari Persemakmuran",
	"concord_day": "Hari Concord",
	"congolese_genocide_day": "Hari Genosida Kongo",
	"constitution_day": "Hari Konstitusi",
	"constitution_memorial_day": "Hari Peringatan Konstitusi",
	"constitutionalist_revolution_of_1932": "Revolusi Konstitusionalis tahun 1932",
	"corpus_christi": "Corpus Christi",
	"culture_day": "Hari Budaya",
	"currency_change_day": "hari perubahan mata uang",
	"cyprus_independence_day": "Hari Kemerdekaan Siprus",
	"cyprus_national_day": "Hari Nasional Siprus",
	"day_after_ascension_day": "Sehari setelah Hari Kenaikan",
	"day_after_new_year_s_day": "Sehari setelah Hari Tahun Baru",
	"day_after_the_commemoration_of_the_assault_of_the_moncada_garrison": "Sehari setelah Peringatan Penyerangan Garnisun Moncada",
	"day_before_the_commemoration_of_the_assault_of_the_moncada_garrison": "Sehari sebelum Peringatan Penyerangan Garnisun Moncada",
	"day_following_the_mid_autumn_festival": "Hari setelah Festival Pertengahan Musim Gugur",
	"day_of_andaluc\u00eda": "Hari Andalusia",
	"day_of_arag\u00f3n": "Hari Arag\u00f3n",
	"day_of_asturias": "Hari Asturias",
	"day_of_castilla_la_mancha": "Hari Castilla La Mancha",
	"day_of_extremadura": "Hari Extremadura",
	"day_of_goodwill": "Hari Kebaikan Hati",
	"day_of_indigenous_resistance": "Hari Perlawanan Masyarakat Adat",
	"day_of_kings": "Hari Raja-Raja",
	"day_of_la_rioja": "Hari La Rioja",
	"day_of_madrid": "Hari Madrid",
	"day_of_murcia": "Hari Murcia",
	"day_of_our_lady_of_the_seven_sorrows": "Hari Raya Bunda Maria Tujuh Dukacita",
	"day_of_peace_and_reconciliation": "Hari Perdamaian dan Rekonsiliasi",
	"day_of_reconciliation": "Hari Rekonsiliasi",
	"day_of_remembrance_for_truth_and_justice": "Hari Peringatan Kebenaran dan Keadilan",
	"day_of_respect_for_cultural_diversity": "Hari Penghormatan terhadap Keragaman Budaya",
	"day_of_restoration_of_independence": "Hari Pemulihan Kemerdekaan",
	"day_of_restoration_of_independence_of_lithuania": "Hari Pemulihan Kemerdekaan Lituania",
	"day_of_svetitskhoveli_cathedra": "Hari Katedral Svetitskhoveli",
	"day_of_the_balearic_islands": "Hari Kepulauan Balearic",
	"day_of_the_canary_islands": "Hari Kepulauan Canary",
	"day_of_the_cantabrian_institutions": "Hari Lembaga-Lembaga Cantabria",
	"day_of_the_constitution_of_the_slovak_republic": "Hari Konstitusi Republik Slovakia",
	"day_of_the_dead": "Hari Orang Mati",
	"day_of_the_establishment_of_the_general_framework_agreement_for_peace_in_bih": "Hari penetapan Kerangka Kerja Umum untuk Perdamaian di Bosnia dan Herzegovina",
	"day_of_the_establishment_of_the_slovak_republic": "Hari Pendirian Republik Slovakia",
	"day_of_the_macedonian_revolutionary_struggle": "Hari Perjuangan Revolusioner Makedonia",
	"day_of_the_maroons": "Hari Maroon",
	"day_of_the_moldovan_national_army": "Hari Tentara Nasional Moldova",
	"day_of_the_queen_of_peace": "Hari Ratu Perdamaian",
	"day_of_the_race": "Hari perlombaan",
	"day_of_the_republic": "Hari Republik",
	"day_of_the_revolution": "Hari Revolusi",
	"day_of_the_valencian_community": "Hari Komunitas Valencia",
	"day_of_the_veterans_and_fallen_of_the_malvinas_war": "Hari Para Veteran dan Korban Perang Malvinas",
	"day_of_uprising_against_occupation": "Hari Pemberontakan Melawan Pendudukan",
	"day_of_valor": "Hari Keberanian",
	"day_of_veterans_of_the_armed_forces_and_law_enforcement_agencies": "Hari Veteran Angkatan Bersenjata dan Lembaga Penegak Hukum",
	"day_of_victory_over_fascism": "Hari Kemenangan atas Fasisme",
	"deceased_ones_day": "Hari orang yang telah meninggal",
	"declaration_of_independence": "Deklarasi Kemerdekaan",
	"declaration_of_independence_of_quito": "Deklarasi Kemerdekaan Quito",
	"deepavali": "Deepavali",
	"defence_forces_day": "Hari Angkatan Pertahanan",
	"defender_of_the_fatherland_day": "Hari Pembela Tanah Air",
	"democracy_and_national_unity_day": "Hari Demokrasi dan Persatuan Nasional",
	"democracy_day": "Hari Demokrasi",
	"dessalines_day": "Hari Dessalines",
	"discovery_day": "Hari Penemuan",
	"discovery_of_puerto_rico": "Penemuan Puerto Rico",
	"diwali": "Diwali",
	"dormition": "Dormisi",
	"dormition_of_the_theotokos": "Dormisi Theotokos",
	"dragon_boat_festival": "Festival Perahu Naga",
	"duarte_s_birthday": "Ulang Tahun Duarte",
	"early_may_bank_holiday": "Libur Bank Awal Mei",
	"earth_day": "Hari Bumi",
	"easter": "Paskah",
	"easter_monday": "Senin Paskah",
	"easter_sunday": "Minggu Paskah",
	"easter_tuesday": "Selasa Paskah",
	"eid_al_adha": "Idul Adha",
	"eid_al_fitr": "EidalFitr",
	"eight_hours_day": "Hari Delapan Jam",
	"emancipation_day": "Hari Emansipasi",
	"enthronement": "Penobatan",
	"epiphany": "Epifani",
	"epiphany_orthodox_": "Epifani (Ortodoks)",
	"errol_barrow_day": "Errol Barrow Day",
	"ethnic_pride_day": "Hari Kebanggaan Etnis",
	"europe_day": "Hari Eropa",
	"evacuation_day": "Hari Evakuasi",
	"family_day": "Hari Keluarga",
	"farmers_day": "Hari Petani",
	"father_s_day": "Hari Ayah",
	"fathers_day": "Hari Ayah",
	"feast_of_our_lady_of_bien_aparecida": "Pesta Bunda Maria Bien Aparecida",
	"feast_of_our_lady_of_the_angels": "Pesta Bunda Maria Para Malaikat",
	"feast_of_our_lady_of_victories": "Pesta Bunda Maria Kemenangan",
	"feast_of_saint_agatha": "Pesta Santo Agatha",
	"feast_of_st_joseph": "Pesta Santo Yosef",
	"feast_of_st_paul_s_shipwreck": "Perayaan Karamnya Kapal Santo Paulus",
	"feast_of_st_peter_and_st_paul": "Pesta Santo Petrus dan Santo Paulus",
	"feast_of_the_divina_pastora": "Perayaan Divina Pastora",
	"feast_of_the_immaculate_conception": "Pesta Maria Dikandung Tanpa Dosa",
	"feast_of_the_immaculate_conception_of_mary": "Pesta Maria Dikandung Tanpa Dosa",
	"feast_of_the_our_lady_of_mercy": "Pesta Bunda Maria Pengasih",
	"feast_of_the_virgin_of_candelaria": "Pesta Perawan Candelaria",
	"federal_day_of_thanksgiving": "Hari Thanksgiving Federal",
	"federal_fast_monday": "Hari Senin Puasa Federal",
	"ferragosto_assumption_": "Ferragosto (Kenaikan)",
	"festival_day": "Hari Raya",
	"festival_of_the_crosses": "Festival Salib",
	"first_day_of_summer": "Hari Pertama Musim Panas",
	"flag_and_universities_day": "Hari Bendera dan Universitas",
	"flag_day": "Hari Bendera",
	"foundation_anniversary_day_of_san_crist\u00f3bal_t\u00e1chira": "Hari Peringatan Yayasan San Crist\u00f3bal, T\u00e1chira",
	"foundation_day": "Hari Pendirian",
	"founders_day": "Hari Pendiri",
	"founding_of_asunci\u00f3n": "Pendirian Asunci\u00f3n",
	"francisco_moraz\u00e1n_s_day_soldier_s_day": "Hari Francisco Moraz\u00e1n/Hari Prajurit",
	"freedom_day": "Hari Kemerdekaan",
	"friday_before_afl_grand_final_tentative_date_": "Jumat sebelum Grand Final AFL (Tanggal Tentatif)",
	"galician_literature_day": "Hari Sastra Galicia",
	"garifuna_settlement_day": "Hari Pemukiman Garifuna",
	"general_jos\u00e9_de_san_mart\u00edn_memorial_day": "Hari Peringatan Jenderal Jos\u00e9 de San Mart\u00edn",
	"general_manuel_belgrano_memorial_day": "Hari Peringatan Jenderal Manuel Belgrano",
	"general_prayer_day": "Hari Doa Umum",
	"geneva_prayday": "Hari Doa Jenewa",
	"genocide_remembrance_day": "Hari Peringatan Genosida",
	"george_price_day": "Hari George Price",
	"german_unity_day": "Hari Persatuan Jerman",
	"gibraltar_national_day": "Hari Nasional Gibraltar",
	"gold_cup_parade_day": "Hari Parade Piala Emas",
	"good_friday": "Jumat Agung",
	"great_patriotic_war_against_fascism_victory_day": "Hari Kemenangan Perang Patriotik Besar Melawan Fasisme",
	"greek_independence_day": "Hari Kemerdekaan Yunani",
	"green_march": "Pawai Hijau",
	"green_monday": "Senin Hijau",
	"greenery_day": "Hari Penghijauan",
	"guru_nanak_gurpurab": "Guru Nanak Gurupurab",
	"halloween": "Halloween",
	"hangul_day": "Hari Hangul",
	"hanukkah": "Hanukkah",
	"hanukkah_day1": "Hari Hanukkah ke-1",
	"hanukkah_day8": "Hanukkah Hari ke-8",
	"hari_raya_haji_tentative_date_": "Hari Raya Haji (Tanggal Sementara)",
	"hari_raya_puasa": "Hari Raya Puasa",
	"hawke_s_bay_anniversary_day": "Hari Peringatan Hawke&#39;s Bay",
	"heritage_day": "Hari Warisan",
	"heroes_day": "Hari Pahlawan",
	"heroes_s_day": "Hari Pahlawan",
	"holi": "Holi",
	"holy_saturday": "Sabtu Suci",
	"holy_thursday": "Kamis Suci",
	"hong_kong_special_administrative_region_establishment_day": "Hari Pendirian Daerah Administratif Khusus Hong Kong",
	"hoshanah_rabbah": "HoshanahRabbah",
	"human_rights_day": "Hari Hak Asasi Manusia",
	"icelandic_national_day": "Hari Nasional Islandia",
	"immaculate_conception": "Dikandung Tanpa Noda",
	"immaculate_conception_day": "Hari Dikandung Tanpa Dosa",
	"independence_and_unity_day": "Hari Kemerdekaan dan Persatuan",
	"independence_day": "hari Kemerdekaan",
	"independence_day_moldova_": "Hari Kemerdekaan (Moldova)",
	"independence_movement_day": "Hari Gerakan Kemerdekaan",
	"independence_of_cartagena": "Kemerdekaan Cartagena",
	"independence_of_cuenca": "Kemerdekaan Cuenca",
	"independence_of_guayaquil": "Kemerdekaan Guayaquil",
	"independent_czechoslovak_state_day": "Hari Negara Cekoslowakia Merdeka",
	"indian_arrival_day": "Hari Kedatangan India",
	"indigenous_people_s_day": "Hari Masyarakat Adat",
	"indigenous_peoples_day": "Hari Masyarakat Adat",
	"indigenous_resistance_day": "Hari Perlawanan Masyarakat Adat",
	"integration_of_primorska_into_the_homeland": "Integrasi Primorska ke dalam Tanah Air",
	"international_day_of_peace": "Hari Perdamaian Internasional",
	"international_women_s_day": "Hari Perempuan Internasional",
	"international_womens_day": "Hari Perempuan Internasional",
	"international_workers_day": "Hari Buruh Internasional",
	"international_working_day": "Hari Kerja Internasional",
	"islander_day": "Hari Penduduk Pulau",
	"jamhuri_day": "Hari Jamhuri",
	"jan_hus_day": "Jan Hus Day",
	"javanese_arrival_day": "Hari Kedatangan Jawa",
	"journalists_day": "Hari Jurnalis",
	"juan_santamar\u00eda_day": "Hari Juan Santamar\u00eda",
	"june_30_revolution": "Revolusi 30 Juni",
	"june_holiday": "Liburan Juni",
	"juneteenth_national_independence_day": "Hari Kemerdekaan Nasional Juneteenth",
	"kadooment_day": "Hari Kadooment",
	"kazakhstan_people_s_unity_day": "Hari Persatuan Rakyat Kazakhstan",
	"keti_koti": "Keti Koti",
	"kimbangu_s_day": "Hari Kimbangu",
	"king_letsie_iii_s_birthday": "Ulang Tahun Raja Letsie III",
	"king_s_birthday": "Hari Ulang Tahun Raja",
	"king_s_day": "Hari Raja",
	"kwanzaa_imani": "KwanzaaImani",
	"kwanzaa_kujichagulia": "KwanzaaKujichagulia",
	"kwanzaa_kuumba": "KwanzaaKuumba",
	"kwanzaa_nia": "KwanzaaNia",
	"kwanzaa_ujamaa": "KwanzaaUjamaa",
	"kwanzaa_ujima": "KwanzaaUjima",
	"kwanzaa_umoja": "KwanzaaUmoja",
	"labour_and_agriculture_day": "Hari Buruh dan Pertanian",
	"labour_day": "Hari Buruh",
	"labour_day_moldova_": "Hari Buruh (Moldova)",
	"labour_thanksgiving_day": "Hari Thanksgiving Buruh",
	"landing_of_the_33_patriots_day": "Pendaratan 33 Patriot Day",
	"lantern_festival": "Festival Lentera",
	"last_day_of_the_year": "Hari Terakhir Tahun Ini",
	"laurent_d\u00e9sir\u00e9_kabila_assassination": "Pembunuhan LaurentD\u00e9sir\u00e9 Kabila",
	"liberation_day": "Hari Pembebasan",
	"liberation_from_fascism": "Pembebasan dari Fasisme",
	"limba_noastra_national_language_day_": "Limba Noastra (Hari Bahasa Nasional)",
	"lincoln_s_birthday": "Hari Ulang Tahun Lincoln",
	"louis_riel_day": "Hari Louis Riel",
	"lunar_new_year": "Tahun Baru Imlek",
	"madaraka_day": "Hari Madaraka",
	"madeira_day": "Hari Madeira",
	"maghi": "Maghi",
	"majority_rule_day": "Hari Pemerintahan Mayoritas",
	"marine_day": "Hari Marinir",
	"marlborough_anniversary_day": "Hari Peringatan Marlborough",
	"martin_luther_king_jr_day": "Hari Martin Luther King, Jr.",
	"martyr_s_day": "Hari Martir",
	"martyrs_day": "Hari Para Martir",
	"mashujaa_day": "Hari Pahlawan",
	"maslenitsa": "Maslenitsa",
	"maslenitsa_start": "MaslenitsaStart",
	"matariki": "Matariki",
	"maundy_thursday": "Kamis Putih",
	"mawlid": "Maulid",
	"may_day": "Hari Buruh",
	"may_day_bank_holiday": "Hari Libur Bank Hari Buruh",
	"may_day_international_workers_day": "Hari Buruh Internasional / Hari Pekerja Internasional",
	"may_revolution": "Revolusi Mei",
	"mazingira_day": "Hari Mazingira",
	"melbourne_cup": "Piala Melbourne",
	"memorial_day": "Hari Peringatan",
	"meskel": "Meskel",
	"mid_autumn_festival": "Festival Pertengahan Musim Gugur",
	"midsummer_day": "Hari Pertengahan Musim Panas",
	"midsummer_eve": "Malam Pertengahan Musim Panas",
	"mimouna": "Mimouna",
	"moshoeshoe_day": "Hari Moshoeshoe",
	"mother_s_day": "hari Ibu",
	"mother_teresa_day": "Hari Bunda Teresa",
	"mothers_day": "Hari Ibu",
	"mountain_day": "Hari Pegunungan",
	"naadam_holiday": "Liburan Naadam",
	"natal_day": "Hari Natal",
	"national_aboriginal_day": "Hari Nasional Masyarakat Adat",
	"national_day": "Hari Nasional",
	"national_day_for_truth_and_reconciliation": "Hari Nasional untuk Kebenaran dan Rekonsiliasi",
	"national_day_great_union": "Hari Nasional/Persatuan Agung",
	"national_day_of_catalonia": "Hari Nasional Katalonia",
	"national_day_of_indigenous_peoples": "Hari Nasional Masyarakat Adat",
	"national_day_of_spain": "Hari Nasional Spanyol",
	"national_day_of_sweden": "Hari Nasional Swedia",
	"national_flag_day": "Hari Bendera Nasional",
	"national_foundation_day": "Hari Pendirian Nasional",
	"national_heroes_and_benefactors_day": "Hari Pahlawan dan Dermawan Nasional",
	"national_heroes_day": "Hari Pahlawan Nasional",
	"national_holiday": "Hari Libur Nasional",
	"national_independence_children_s_day": "Hari Kemerdekaan Nasional &amp; Hari Anak",
	"national_patriots_day": "Hari Patriot Nasional",
	"national_pupusa_festival": "Festival Pupusa Nasional",
	"national_sovereignty_day": "Hari Kedaulatan Nasional",
	"national_unity_day": "Hari Persatuan Nasional",
	"national_women_s_day": "Hari Perempuan Nasional",
	"national_youth_day": "Hari Pemuda Nasional",
	"nativity_of_our_lady": "Kelahiran Bunda Maria",
	"nauryz_meyramy": "Nauryz Meyramy",
	"navy_day": "Hari Angkatan Laut",
	"nelson_anniversary_day": "Hari Peringatan Nelson",
	"new_brunswick_day": "Hari New Brunswick",
	"new_year_holiday": "Liburan Tahun Baru",
	"new_year_s_day": "Hari Tahun Baru",
	"new_year_s_eve": "malam tahun baru",
	"new_years_eve": "Malam tahun baru",
	"nigerien_independence_day": "Hari Kemerdekaan Niger",
	"nigerien_republic_day": "Hari Republik Niger",
	"ninoy_aquino_day": "Hari Ninoy Aquino",
	"nowruz": "Nowruz",
	"n\u00e4fels_procession": "Prosesi N\u00e4fels",
	"ochi_day": "Hari Ochi",
	"october_holiday": "Liburan Oktober",
	"october_revolution_day": "Hari Revolusi Oktober",
	"ohi_day": "Ohi Day",
	"old_new_year": "Tahun Baru Lama",
	"orangemen_s_day": "Hari Orangemen",
	"otago_anniversary_day": "Hari Peringatan Otago",
	"our_lady_of_altagracia": "Bunda Maria dari Altagracia",
	"our_lady_of_aparecida": "Bunda Maria dari Aparecida",
	"our_lady_of_mercy": "Bunda Maria Pengasih",
	"our_lady_of_mount_carmel": "Bunda Maria dari Gunung Karmel",
	"pan_america_day": "Hari Pan Amerika",
	"pancasila_day": "Hari Pancasila",
	"paraguayan_independence": "Kemerdekaan Paraguay",
	"parents_day": "Hari Orang Tua",
	"pascha": "Paskah",
	"passover": "Paskah",
	"passover_day1": "Hari Paskah Pertama",
	"passover_day2": "Hari Paskah ke-2",
	"passover_day7": "Hari Paskah ke-7",
	"passover_day8": "Paskah Hari ke-8",
	"patrice_lumumba_assassination": "Pembunuhan Patrice Lumumba",
	"pentecost": "Pantekosta",
	"perry_christie_day": "Hari Perry Christie",
	"picnic_day": "Hari Piknik",
	"presidents_day": "Hari Presiden",
	"pre\u0161eren_day": "Hari Pre\u0161eren",
	"primo\u017e_trubar_day": "Primo\u017e Trubar Day",
	"proclamation_day_of_the_republic_of_latvia": "Hari Proklamasi Republik Latvia",
	"proclamation_of_independence": "Proklamasi Kemerdekaan",
	"puerto_rico_constitution_day": "Hari Konstitusi Puerto Rico",
	"qingming_festival": "Festival Qingming",
	"queen_s_birthday": "Hari Ulang Tahun Ratu",
	"rama_navami": "RamaNavami",
	"ramadan_start": "Ramadan Dimulai",
	"reconciliation_day": "Hari Rekonsiliasi",
	"reformation_day": "Hari Reformasi",
	"remembrance_day": "Hari Peringatan",
	"renovation_day": "Hari Renovasi",
	"repentance_and_prayer_day": "Hari Pertobatan dan Doa",
	"repentance_day": "Hari Pertobatan",
	"republic_day": "Hari Republik",
	"republic_proclamation_day": "Hari Proklamasi Republik",
	"respect_for_the_aged_day": "Hari Penghormatan untuk Lansia",
	"restoration_day": "Hari Pemulihan",
	"restoration_of_independence": "Pemulihan Kemerdekaan",
	"restoration_of_independence_day": "Pemulihan Hari Kemerdekaan",
	"reunification_day": "Hari Penyatuan Kembali",
	"revolution_day": "Hari Revolusi",
	"revolution_day_2011_national_police_day": "Hari Revolusi 2011 / Hari Kepolisian Nasional",
	"revolution_of_the_king_and_the_people": "Revolusi Raja dan Rakyat",
	"rizal_day": "Hari Rizal",
	"robert_mugabe_national_youth_day": "Hari Pemuda Nasional Robert Mugabe",
	"rosh_hashanah": "Rosh HaShanah",
	"rosh_hashanah_day1": "Rosh Hashanah Hari ke-1",
	"rosh_hashanah_day2": "Rosh Hashanah Hari ke-2",
	"rudolf_maister_day": "Rudolf Maister Day",
	"russia_day": "Hari Rusia",
	"sacred_heart": "Hati Kudus",
	"saint_andrew_s_day": "Hari Santo Andreas",
	"saint_andrew_the_first_called_day": "Hari Santo Andreas yang Pertama Dipanggil",
	"saint_brigid_s_day": "Hari Santo Brigid",
	"saint_clement_of_ohrid_day": "Hari Santo Klemens dari Ohrid",
	"saint_devota_s_day": "Hari Santo Devota",
	"saint_george_s_caye_day": "Hari Saint George&#39;s Caye",
	"saint_george_s_day": "Hari Santo Georgius",
	"saint_john_the_baptist": "Santo Yohanes Pembaptis",
	"saint_joseph_s_day": "Hari Santo Yosef",
	"saint_mary_s_day": "Hari Santa Maria",
	"saint_olav_s_day": "Hari Santo Olav",
	"saint_olav_s_eve": "Malam sebelum Hari Raya Santo Olav",
	"saint_patrick_s_day": "Hari Santo Patrick",
	"saint_peter_and_saint_paul": "Santo Petrus dan Santo Paulus",
	"saints_cyril_and_methodius_day": "Hari Santo Cyril dan Methodius",
	"santa_rosa_de_lima": "Santa Rosa de Lima",
	"santiago_ap\u00f3stol": "Santiago Apostol",
	"saskatchewan_day": "Hari Saskatchewan",
	"second_day_of_christmas": "Hari kedua Natal",
	"second_day_of_lunar_new_year": "Hari kedua Tahun Baru Imlek",
	"separation_day": "Hari Perpisahan",
	"sette_giugno": "Sette Giugno",
	"shavuot": "Shavuot",
	"shavuot_day1": "Hari Shavuot1",
	"shavuot_day2": "Shavuot Hari ke-2",
	"shemini_atzeret": "SheminiAtzeret",
	"shout_in_villa_de_los_santos": "Teriak di Villa de los Santos",
	"shrove_tuesday": "Selasa Shrove",
	"sh\u014dwa_day": "Hari Showa",
	"simchat_torah": "SimchatTorah",
	"sim\u00f3n_bol\u00edvar_s_birthday": "Ulang Tahun Sim\u00f3n Bol\u00edvar",
	"sinai_liberation_day": "Hari Pembebasan Sinai",
	"sir_seretse_khama_day": "Sir Seretse Khama Day",
	"slavery_abolition_anniversary": "Peringatan Penghapusan Perbudakan",
	"slovak_national_uprising_anniversary": "Peringatan Pemberontakan Nasional Slovakia",
	"slovenian_sports_day": "Hari Olahraga Slovenia",
	"soldiers_day": "Hari Prajurit",
	"songkran": "Songkran",
	"songkran_day1": "Hari Songkran Pertama",
	"songkran_day2": "Hari Songkran ke-2",
	"songkran_day3": "Songkran Hari ke-3",
	"south_capital_s_day_cahul": "Day Cahul dari South Capital",
	"southland_anniversary_day": "Hari Peringatan Southland",
	"sovereign_s_birthday": "Ulang tahun penguasa",
	"sovereignty_day": "Hari Kedaulatan",
	"sports_day": "Hari Olahraga",
	"spring_bank_holiday": "Libur Bank Musim Semi",
	"spring_day": "Hari Musim Semi",
	"st_andrew_s_day": "Hari Santo Andreas",
	"st_berchtold_s_day": "Hari Santo Berchtold",
	"st_cyril_and_methodius_day": "Hari Santo Cyril dan Methodius",
	"st_francis_of_assisi_s_day": "Hari Santo Fransiskus dari Assisi",
	"st_john_s_day": "Hari Santo Yohanes",
	"st_stephen_s_day": "Hari Santo Stefanus",
	"st_wenceslas_day": "Hari Santo Wenceslas",
	"state_foundation_day": "Hari Pendirian Negara",
	"statehood_day": "Hari Pendirian Negara Bagian",
	"struggle_for_freedom_and_democracy_day": "Hari Perjuangan untuk Kebebasan dan Demokrasi",
	"sukkot": "Sukkot",
	"sukkot_day1": "SukkotHari1",
	"sukkot_day2": "Sukkot Hari ke-2",
	"summer_bank_holiday": "Libur Bank Musim Panas",
	"summer_day": "Hari Musim Panas",
	"swiss_national_day": "Hari Nasional Swiss",
	"taranaki_anniversary_day": "Hari Peringatan Taranaki",
	"teacher_s_day": "Hari Guru",
	"thanksgiving": "Hari Thanksgiving",
	"thanksgiving_day": "Hari Thanksgiving",
	"the_battle_of_pichincha": "Pertempuran Pichincha",
	"the_day_of_restoration_of_the_state_of_lithuania": "Hari Pemulihan Negara Lituania",
	"the_day_of_the_cross": "Hari Salib",
	"the_emperor_s_birthday": "Hari Ulang Tahun Kaisar",
	"the_feast_of_san_marino_and_the_republic": "Perayaan Santo Marino dan Republik",
	"the_immaculate_conception": "Dikandung Tanpa Dosa",
	"theophany": "Teofani",
	"third_day_of_lunar_new_year": "Hari ketiga Tahun Baru Imlek",
	"three_kings_day": "Hari Tiga Raja",
	"three_kings_day_epiphany": "Hari Tiga Raja / Epifani",
	"tiradentes": "Tiradentes",
	"traditional_day": "Hari Tradisional",
	"triumph_of_the_revolution": "Kemenangan Revolusi",
	"truman_day": "Hari Truman",
	"tu_bav": "TubAv",
	"ullortuneq": "Ullortuneq",
	"unification_day": "Hari Penyatuan",
	"unification_of_prekmurje_slovenes_with_the_mother_nation": "Penyatuan warga Slovenia Prekmurje dengan negara induk.",
	"union_day_small_union": "Hari Persatuan/Serikat Pekerja Kecil",
	"unity_day": "Hari Persatuan",
	"vaisakhi": "Vaisakhi",
	"valentines_day": "Hari Valentine",
	"vernal_equinox_day": "Hari Ekuinoks Musim Semi",
	"vesak_day": "Hari Vesak",
	"veterans_day": "Hari Veteran",
	"victoria_day": "Hari Victoria",
	"victory_and_commemoration_day": "Hari Kemenangan dan Peringatan",
	"victory_and_homeland_thanksgiving_day_and_the_day_of_croatian_defenders": "Hari Kemenangan dan Syukur Tanah Air serta Hari Para Pembela Kroasia",
	"victory_and_peace_day": "Hari Kemenangan dan Perdamaian",
	"victory_day": "Hari Kemenangan",
	"victory_day_over_fascism": "Hari Kemenangan atas fasisme",
	"victory_in_europe_day": "Hari Kemenangan di Eropa",
	"victory_of_fidel_castro": "Kemenangan Fidel Castro",
	"virgin_of_caacupe": "Perawan Caacupe",
	"waitangi_day": "Hari Waitangi",
	"wellington_anniversary_day": "Hari Peringatan Wellington",
	"western_australia_day": "Hari Australia Barat",
	"westland_anniversary_day": "Hari Peringatan Westland",
	"whit_monday": "Senin Putih",
	"women_s_day": "Hari Perempuan",
	"worker_s_day": "Hari Buruh",
	"workers_day": "Hari Buruh",
	"workers_memorial_day": "Hari Peringatan Pekerja",
	"world_children_s_day": "Hari Anak Sedunia",
	"world_religion_day": "Hari Agama Sedunia",
	"yom_kippur": "Yom Kippur",
	"youth_day": "Hari Pemuda",
	"zikra_oued_ed_dahab": "Zikra Oued EdDahab",
	"tisha_bav": "TishabAv"
}